nyogyi_pretty_xml/__init__.py
nyogyi_pretty_xml/nyogyi_pretty_xml.py
nyogyi_pretty_xml-0.1.1.dist-info/LICENSE
nyogyi_pretty_xml-0.1.1.dist-info/METADATA
nyogyi_pretty_xml-0.1.1.dist-info/WHEEL
nyogyi_pretty_xml-0.1.1.dist-info/entry_points.txt
nyogyi_pretty_xml-0.1.1.dist-info/top_level.txt
nyogyi_pretty_xml-0.1.1.dist-info/RECORD
