Metadata-Version: 2.1
Name: nyogyi-pretty-xml
Version: 0.1.1
Summary: A script to pretty print large XML files
Home-page: https://pypi.org/project/nyogyi-pretty-xml/
Author: Thein Htike Nyo
Author-email: theinhtitenyo@gmail.com
License: UNKNOWN
Platform: UNKNOWN
Classifier: Programming Language :: Python :: 3
Classifier: License :: OSI Approved :: MIT License
Classifier: Operating System :: OS Independent
Requires-Python: >=3.6
License-File: LICENSE
Requires-Dist: lxml
